toolkit_requests/__init__.py
toolkit_requests/requests_util.py
toolkit_requests-0.0.1.dist-info/METADATA
toolkit_requests-0.0.1.dist-info/WHEEL
toolkit_requests-0.0.1.dist-info/top_level.txt
toolkit_requests-0.0.1.dist-info/RECORD
