Metadata-Version: 2.1
Name: toolkit-requests
Version: 0.0.1
Summary: Typosquatting talk example, do not use.
Home-page: https://github.com/requests/toolbelt
Author: N. Body
Author-email: nepijav923@otanhome.com
License: Apache
Classifier: Programming Language :: Python
Classifier: Programming Language :: Python :: 3
